pyintelxio/__init__.py
pyintelxio/intelx.py
pyintelxio-1.0.1.dist-info/METADATA
pyintelxio-1.0.1.dist-info/WHEEL
pyintelxio-1.0.1.dist-info/top_level.txt
pyintelxio-1.0.1.dist-info/RECORD
