Metadata-Version: 2.1
Name: pyintelxio
Version: 1.0.1
Summary: Un servicio para usar las api de IntelligenceX
Author: Fermin
License: MIT
Keywords: python,package,distribution
Requires-Dist: requests
